LICENSE
MANIFEST.in
README.rst
setup.py
django_image_styles.egg-info/PKG-INFO
django_image_styles.egg-info/SOURCES.txt
django_image_styles.egg-info/dependency_links.txt
django_image_styles.egg-info/not-zip-safe
django_image_styles.egg-info/requires.txt
django_image_styles.egg-info/top_level.txt
image_styles/__init__.py
image_styles/admin.py
image_styles/forms.py
image_styles/models.py
image_styles/tests.py
image_styles/urls.py
image_styles/utils.py
image_styles/views.py
image_styles/fixtures/0001_initial.json
image_styles/migrations/0001_initial.py
image_styles/migrations/__init__.py
image_styles/templates/image_styles/bootstrap_form_modal.html
image_styles/templates/image_styles/generic_form.html
image_styles/templates/image_styles/manage_image_styles.html
image_styles/templatetags/__init__.py
image_styles/templatetags/image_styles.py