Metadata-Version: 1.1
Name: django-image-styles
Version: 1.2.2
Summary: Django image formatting tool.
Home-page: https://github.com/devalfrz/django-image-styles
Author: Alfredo Rius
Author-email: alfredo.rius@gmail.com
License: BSD
Platform: UNKNOWN
Classifier: Development Status :: 5 - Production/Stable
Classifier: Environment :: Web Environment
Classifier: Framework :: Django
Classifier: Intended Audience :: Developers
Classifier: License :: OSI Approved :: BSD License
Classifier: Operating System :: OS Independent
Classifier: Programming Language :: Python
Classifier: Programming Language :: Python :: 3
Classifier: Topic :: Internet :: WWW/HTTP
